pyodide_httpx-0.1.1.dist-info/METADATA
pyodide_httpx-0.1.1.dist-info/WHEEL
pyodide_httpx-0.1.1.dist-info/licenses/LICENSE
pyodide_httpx/__init__.py
pyodide_httpx/_async.py
pyodide_httpx/_sync.py
pyodide_httpx/utils/sync.py
pyodide_httpx-0.1.1.dist-info/RECORD
