Metadata-Version: 2.1
Name: pyodide-httpx
Version: 0.1.1
Summary: patch httpx for using in pyodide
License: Mozilla Public License Version 2.0
Classifier: Programming Language :: Python :: 3
Classifier: License :: OSI Approved :: Mozilla Public License 2.0 (MPL 2.0)
Classifier: Operating System :: OS Independent
Requires-Python: >=3.12
Requires-Dist: httpx>=0.25.1
